[
  {
    "inputs": [],
    "stateMutability": "nonpayable",
    "type": "constructor"
  },
  {
    "inputs": [
      {
        "internalType": "address",
        "name": "_certificate",
        "type": "address"
      }
    ],
    "name": "addCertificate",
    "outputs": [],
    "stateMutability": "nonpayable",
    "type": "function"
  },
  {
    "inputs": [
      {
        "internalType": "address",
        "name": "_certificate",
        "type": "address"
      }
    ],
    "name": "addCertifiedCertificate",
    "outputs": [],
    "stateMutability": "nonpayable",
    "type": "function"
  },
  {
    "inputs": [],
    "name": "getCertificates",
    "outputs": [
      {
        "internalType": "address[]",
        "name": "certificates",
        "type": "address[]"
      }
    ],
    "stateMutability": "view",
    "type": "function"
  },
  {
    "inputs": [],
    "name": "getCertifiedCertificates",
    "outputs": [
      {
        "internalType": "address[]",
        "name": "certifiedCerts",
        "type": "address[]"
      }
    ],
    "stateMutability": "view",
    "type": "function"
  }
]